lifesospy_mqtt/__init__.py
lifesospy_mqtt/__main__.py
lifesospy_mqtt/config.py
lifesospy_mqtt/const.py
lifesospy_mqtt/enums.py
lifesospy_mqtt/logger.py
lifesospy_mqtt/subscribetopic.py
lifesospy_mqtt/translator.py
lifesospy_mqtt-0.11.6.dist-info/LICENSE
lifesospy_mqtt-0.11.6.dist-info/METADATA
lifesospy_mqtt-0.11.6.dist-info/WHEEL
lifesospy_mqtt-0.11.6.dist-info/entry_points.txt
lifesospy_mqtt-0.11.6.dist-info/top_level.txt
lifesospy_mqtt-0.11.6.dist-info/RECORD
