Metadata-Version: 2.1
Name: lifesospy-mqtt
Version: 0.11.6
Summary: MQTT client to report state of LifeSOS security system and devices.
Home-page: https://github.com/rorr73/lifesospy_mqtt
Author: Richard Orr
License: UNKNOWN
Platform: UNKNOWN
Classifier: Development Status :: 3 - Alpha
Classifier: Environment :: Other Environment
Classifier: Intended Audience :: End Users/Desktop
Classifier: Operating System :: OS Independent
Classifier: Programming Language :: Python
Classifier: Topic :: Home Automation
Classifier: Topic :: Security
Requires-Python: >=3.5.3
Requires-Dist: janus (~=0.4.0)
Requires-Dist: lifesospy (~=0.10.1)
Requires-Dist: paho-mqtt (~=1.4.0)
Requires-Dist: python-daemon (~=2.2.4)
Requires-Dist: python-dateutil (>=2.7.5)
Requires-Dist: pyyaml (>=4.2b1)
